MANIFEST.in
setup.cfg
setup.py
scrypture/__init__.py
scrypture/default_config.py
scrypture/scrypture.py
scrypture/scrypture_api.py
scrypture/webapi.py
scrypture.egg-info/PKG-INFO
scrypture.egg-info/SOURCES.txt
scrypture.egg-info/dependency_links.txt
scrypture.egg-info/not-zip-safe
scrypture.egg-info/requires.txt
scrypture.egg-info/top_level.txt
scrypture/bin/run_scrypture.py
scrypture/demo_scripts/__init__.py
scrypture/demo_scripts/template.py
scrypture/demo_scripts/Demos/__init__.py
scrypture/demo_scripts/Demos/api_demo.py
scrypture/demo_scripts/Demos/silly_demo.py
scrypture/demo_scripts/Network/__init__.py
scrypture/demo_scripts/Network/enumerate_ips.py
scrypture/demo_scripts/Network/nmap_to_csv.py
scrypture/demo_scripts/Security/__init__.py
scrypture/demo_scripts/Security/file_hash.py
scrypture/demo_scripts/Security/quick_hash.py
scrypture/demo_scripts/Text/__init__.py
scrypture/demo_scripts/Text/camelcase_to_underscores.py
scrypture/demo_scripts/Text/reverse_characters.py
scrypture/demo_scripts/Text/reverse_words.py
scrypture/demo_scripts/Text/shuffle_characters.py
scrypture/demo_scripts/Text/shuffle_words.py
scrypture/demo_scripts/Text/text_to_lower.py
scrypture/demo_scripts/Text/text_to_upper.py
scrypture/demo_scripts/Text/uniq.py
scrypture/demo_scripts/Utils/__init__.py
scrypture/demo_scripts/Utils/b64encode.py
scrypture/demo_scripts/Utils/bytes_to_human.py
scrypture/demo_scripts/Utils/convert_epoch_time.py
scrypture/demo_scripts/Utils/curl_to_requests.py
scrypture/demo_scripts/Utils/js_pretty_print.py
scrypture/demo_scripts/Utils/json_pretty_print.py
scrypture/demo_scripts/Utils/json_to_csv.py
scrypture/demo_scripts/Utils/curl2requests/__init__.py
scrypture/demo_scripts/Utils/curl2requests/curl_help.py
scrypture/demo_scripts/Utils/curl2requests/curl_to_requests.py
scrypture/demo_scripts/Utils/curl2requests/test_curl_to_requests.py
scrypture/static/__init__.py
scrypture/static/color_palette.html
scrypture/static/dark.css
scrypture/static/github.css
scrypture/static/highlight.js
scrypture/static/scrypture-48.png
scrypture/static/scrypture.ico
scrypture/static/scrypture.png
scrypture/static/scrypture.svg
scrypture/static/scrypture_logo.png
