Metadata-Version: 1.1
Name: scrypture
Version: 0.2.8
Summary: Automatically serve Python scripts through a web interface and REST API.
Home-page: https://github.com/mosesschwartz/curl_to_requests
Author: Moses Schwartz
Author-email: moses.schwartz@gmail.com
License: MIT
Keywords: webapp api framework
Platform: UNKNOWN
Classifier: Development Status :: 3 - Alpha
Classifier: Intended Audience :: Developers
Classifier: Topic :: Software Development
Classifier: Topic :: Utilities
Classifier: License :: OSI Approved :: MIT License
Classifier: Programming Language :: Python :: 2
Classifier: Programming Language :: Python :: 2.7
